Metadata-Version: 2.4
Name: data_gatherer
Version: 0.1.8
Summary: DataGatherer Library
Author-email: Pietro Marini <pgm7072@nyu.edu>
Maintainer-email: Pietro Marini <pgm7072@nyu.edu>
License: MIT
Project-URL: Homepage, https://github.com/VIDA-NYU/data-gatherer
Project-URL: Repository, https://github.com/VIDA-NYU/data-gatherer
Project-URL: Issues, https://github.com/VIDA-NYU/data-gatherer/issues
Keywords: Information Extraction,NYU
Classifier: Development Status :: 4 - Beta
Classifier: Intended Audience :: Developers
Classifier: Operating System :: OS Independent
Classifier: Programming Language :: Python :: 3
Classifier: Programming Language :: Python :: 3.11
Classifier: Programming Language :: Python :: 3.12
Classifier: Topic :: Scientific/Engineering :: Information Analysis
Requires-Python: >=3.11
Requires-Dist: beautifulsoup4>=4.12.3
Requires-Dist: bs4
Requires-Dist: lxml
Requires-Dist: numpy
Requires-Dist: ollama
Requires-Dist: openai
Requires-Dist: pandas
Requires-Dist: pydantic
Requires-Dist: pydantic_core
Requires-Dist: python-dotenv
Requires-Dist: PyYAML
Requires-Dist: regex
Requires-Dist: requests
Requires-Dist: selenium>=4.28.0
Requires-Dist: tokenizers
Requires-Dist: transformers
Requires-Dist: typing_extensions
Requires-Dist: webdriver-manager
Requires-Dist: google-generativeai
Requires-Dist: tiktoken
Requires-Dist: cloudscraper
Requires-Dist: pyui
Requires-Dist: pysdl2-dll
Requires-Dist: streamlit
Requires-Dist: ipywidgets
Requires-Dist: portkey-ai
Requires-Dist: xlsxwriter
Requires-Dist: sentence-transformers
Requires-Dist: pymupdf
Requires-Dist: json-repair
